urlexpander_custom/__init__.py
urlexpander_custom/core/__init__.py
urlexpander_custom/core/api.py
urlexpander_custom/core/constants.py
urlexpander_custom/core/datasets.py
urlexpander_custom/core/html_utils.py
urlexpander_custom/core/tweet_utils.py
urlexpander_custom-0.0.4.dist-info/LICENSE
urlexpander_custom-0.0.4.dist-info/METADATA
urlexpander_custom-0.0.4.dist-info/WHEEL
urlexpander_custom-0.0.4.dist-info/top_level.txt
urlexpander_custom-0.0.4.dist-info/RECORD
