Metadata-Version: 2.1
Name: urlexpander-custom
Version: 0.0.4
Summary: urlExpander is a Python package for quickly and thoroughly expanding shortened URLs.
Author-email: leon yin <author@example.com>
Project-URL: Homepage, https://github.com/SMAPPNYU/urlExpander
Classifier: Programming Language :: Python :: 3
Classifier: License :: OSI Approved :: MIT License
Classifier: Operating System :: OS Independent
Requires-Python: >=3.7
License-File: LICENSE
